[
  {
    "id": 1,
    "flightNumber": "561",
    "date": "2025-10-25",
    "from": "SFO-San Francisco Airport",
    "to": "SAL-El Salvador Airport",
    "status": "Landed",
    "etd": "00:05",
    "atd": "00:11",
    "airline": "Taca",
    "delayMinutes": 6,
    "delayCategory": "+ 6",
    "lastUpdated": "2025-10-25T11:14:23.000Z"
  },
  {
    "id": 2,
    "flightNumber": "245",
    "date": "2025-10-25",
    "from": "JFK-John F Kennedy",
    "to": "BOG-El Dorado Airport",
    "status": "Landed",
    "etd": "00:30",
    "atd": "02:27",
    "airline": "Avianca",
    "delayMinutes": 117,
    "delayCategory": "+ 117",
    "lastUpdated": "2025-10-25T11:14:23.000Z"
  },
  {
    "id": 3,
    "flightNumber": "187",
    "date": "2025-10-25",
    "from": "MEX-Benito Juarez Airport",
    "to": "BOG-El Dorado Airport",
    "status": "Landed",
    "etd": "00:40",
    "atd": "00:49",
    "airline": "Avianca",
    "delayMinutes": 9,
    "delayCategory": "+ 9",
    "lastUpdated": "2025-10-25T11:14:23.000Z"
  },
  {
    "id": 4,
    "flightNumber": "218",
    "date": "2025-10-25",
    "from": "EZE-Ezeiza Ministro Pistarini Airport",
    "to": "BOG-El Dorado Airport",
    "status": "Landed",
    "etd": "01:40",
    "atd": "01:46",
    "airline": "Wamos",
    "delayMinutes": 6,
    "delayCategory": "+ 6",
    "lastUpdated": "2025-10-25T11:14:23.000Z"
  },
  {
    "id": 5,
    "flightNumber": "428",
    "date": "2025-10-25",
    "from": "LIM-Jorge Chavez Airport",
    "to": "SAL-El Salvador Airport",
    "status": "Landed",
    "etd": "01:40",
    "atd": "01:48",
    "airline": "Taca",
    "delayMinutes": 8,
    "delayCategory": "+ 8",
    "lastUpdated": "2025-10-25T11:14:23.000Z"
  },
  {
    "id": 6,
    "flightNumber": "248",
    "date": "2025-10-25",
    "from": "GRU-Sao Pablo- Guarulhos Airport",
    "to": "BOG-El Dorado Airport",
    "status": "Landed",
    "etd": "01:45",
    "atd": "02:14",
    "airline": "Avianca",
    "delayMinutes": 29,
    "delayCategory": "+ 29",
    "lastUpdated": "2025-10-25T11:14:23.000Z"
  },
  {
    "id": 7,
    "flightNumber": "7393",
    "date": "2025-10-25",
    "from": "JFK-John F Kennedy",
    "to": "GYE-José Joaquín de Olmedo Airport",
    "status": "Landed",
    "etd": "02:00",
    "atd": "01:58",
    "airline": "Avianca Ecuador",
    "delayMinutes": -2,
    "delayCategory": "Early 2",
    "lastUpdated": "2025-10-25T11:14:23.000Z"
  },
  {
    "id": 8,
    "flightNumber": "112",
    "date": "2025-10-25",
    "from": "EZE-Ezeiza Ministro Pistarini Airport",
    "to": "MDE-Jose Maria Cordova Airport",
    "status": "Landed",
    "etd": "02:30",
    "atd": "03:19",
    "airline": "Avianca",
    "delayMinutes": 49,
    "delayCategory": "+ 49",
    "lastUpdated": "2025-10-25T11:14:23.000Z"
  },
  {
    "id": 9,
    "flightNumber": "66",
    "date": "2025-10-25",
    "from": "UIO-Mariscal Sucre Airport",
    "to": "BOG-El Dorado Airport",
    "status": "Landed",
    "etd": "02:30",
    "atd": "02:22",
    "airline": "Avianca",
    "delayMinutes": -8,
    "delayCategory": "Early 8",
    "lastUpdated": "2025-10-25T11:14:23.000Z"
  },
  {
    "id": 10,
    "flightNumber": "166",
    "date": "2025-10-25",
    "from": "VVI-Viru Viru Airport",
    "to": "BOG-El Dorado Airport",
    "status": "Landed",
    "etd": "02:50",
    "atd": "02:50",
    "airline": "Avianca",
    "delayMinutes": 0,
    "delayCategory": "Early 0",
    "lastUpdated": "2025-10-25T11:14:23.000Z"
  },
  {
    "id": 11,
    "flightNumber": "224",
    "date": "2025-10-25",
    "from": "LPB-El Alto Airport",
    "to": "BOG-El Dorado Airport",
    "status": "Landed",
    "etd": "03:20",
    "atd": "03:18",
    "airline": "Avianca",
    "delayMinutes": -2,
    "delayCategory": "Early 2",
    "lastUpdated": "2025-10-25T11:14:23.000Z"
  },
  {
    "id": 12,
    "flightNumber": "82",
    "date": "2025-10-25",
    "from": "MAO-Eduardo Gomes Airport",
    "to": "BOG-El Dorado Airport",
    "status": "Landed",
    "etd": "04:05",
    "atd": "03:41",
    "airline": "Avianca",
    "delayMinutes": -24,
    "delayCategory": "Early 24",
    "lastUpdated": "2025-10-25T11:14:23.000Z"
  },
  {
    "id": 13,
    "flightNumber": "9653",
    "date": "2025-10-25",
    "from": "MDE-Jose Maria Cordova Airport",
    "to": "BOG-El Dorado Airport",
    "status": "Landed",
    "etd": "04:23",
    "atd": "04:21",
    "airline": "Avianca",
    "delayMinutes": -2,
    "delayCategory": "Early 2",
    "lastUpdated": "2025-10-25T11:14:23.000Z"
  },
  {
    "id": 14,
    "flightNumber": "235",
    "date": "2025-10-25",
    "from": "MEX-Benito Juarez Airport",
    "to": "MDE-Jose Maria Cordova Airport",
    "status": "Landed",
    "etd": "05:00",
    "atd": "05:02",
    "airline": "Avianca",
    "delayMinutes": 2,
    "delayCategory": "+ 2",
    "lastUpdated": "2025-10-25T11:14:23.000Z"
  },
  {
    "id": 15,
    "flightNumber": "8546",
    "date": "2025-10-25",
    "from": "MDE-Jose Maria Cordova Airport",
    "to": "BAQ-Ernesto Cortissoz Airport",
    "status": "Landed",
    "etd": "05:00",
    "atd": "04:56",
    "airline": "Avianca",
    "delayMinutes": -4,
    "delayCategory": "Early 4",
    "lastUpdated": "2025-10-25T11:14:23.000Z"
  },
  {
    "id": 16,
    "flightNumber": "8409",
    "date": "2025-10-25",
    "from": "BOG-El Dorado Airport",
    "to": "CLO-Alfonso Bonilla Aragón Airport",
    "status": "Landed",
    "etd": "05:10",
    "atd": "05:03",
    "airline": "Avianca",
    "delayMinutes": -7,
    "delayCategory": "Early 7",
    "lastUpdated": "2025-10-25T11:14:23.000Z"
  },
  {
    "id": 17,
    "flightNumber": "8593",
    "date": "2025-10-25",
    "from": "CLO-Alfonso Bonilla Aragón Airport",
    "to": "BAQ-Ernesto Cortissoz Airport",
    "status": "Landed",
    "etd": "05:20",
    "atd": "05:10",
    "airline": "Avianca",
    "delayMinutes": -10,
    "delayCategory": "Early 10",
    "lastUpdated": "2025-10-25T11:14:23.000Z"
  },
  {
    "id": 18,
    "flightNumber": "1690",
    "date": "2025-10-25",
    "from": "UIO-Mariscal Sucre Airport",
    "to": "MEC-Eloy Alfaro Airport",
    "status": "Landed",
    "etd": "06:00",
    "atd": "05:47",
    "airline": "Avianca Ecuador",
    "delayMinutes": -13,
    "delayCategory": "Early 13",
    "lastUpdated": "2025-10-25T11:14:23.000Z"
  },
  {
    "id": 19,
    "flightNumber": "9491",
    "date": "2025-10-25",
    "from": "BOG-El Dorado Airport",
    "to": "LET-Alfredo Vasquez Cobo Airport",
    "status": "Landed",
    "etd": "06:10",
    "atd": "06:11",
    "airline": "Avianca",
    "delayMinutes": 1,
    "delayCategory": "+ 1",
    "lastUpdated": "2025-10-25T11:14:23.000Z"
  },
  {
    "id": 20,
    "flightNumber": "640",
    "date": "2025-10-25",
    "from": "SJO-Juan Santamaria Airport",
    "to": "GUA-La Aurora Airport",
    "status": "Landed",
    "etd": "06:10",
    "atd": "06:01",
    "airline": "Avianca Costa Rica",
    "delayMinutes": -9,
    "delayCategory": "Early 9",
    "lastUpdated": "2025-10-25T11:14:23.000Z"
  },
  {
    "id": 21,
    "flightNumber": "640",
    "date": "2025-10-25",
    "from": "GUA-La Aurora Airport",
    "to": "LAX-Los Angeles Airport",
    "status": "Departed",
    "etd": "09:00",
    "atd": "08:54",
    "airline": "Avianca Costa Rica",
    "delayMinutes": -6,
    "delayCategory": "Early 6",
    "lastUpdated": "2025-10-25T11:14:23.000Z"
  },
  {
    "id": 22,
    "flightNumber": "49",
    "date": "2025-10-25",
    "from": "BOG-El Dorado Airport",
    "to": "LIM-Jorge Chavez Airport",
    "status": "Landed",
    "etd": "06:25",
    "atd": "06:17",
    "airline": "Avianca",
    "delayMinutes": -8,
    "delayCategory": "Early 8",
    "lastUpdated": "2025-10-25T11:14:23.000Z"
  },
  {
    "id": 23,
    "flightNumber": "43",
    "date": "2025-10-25",
    "from": "JFK-John F Kennedy",
    "to": "MDE-Jose Maria Cordova Airport",
    "status": "Departed",
    "etd": "06:30",
    "atd": "07:25",
    "airline": "Avianca",
    "delayMinutes": 55,
    "delayCategory": "+ 55",
    "lastUpdated": "2025-10-25T11:14:23.000Z"
  },
  {
    "id": 24,
    "flightNumber": "8397",
    "date": "2025-10-25",
    "from": "BOG-El Dorado Airport",
    "to": "GYE-José Joaquín de Olmedo Airport",
    "status": "Landed",
    "etd": "06:40",
    "atd": "06:40",
    "airline": "Avianca Ecuador",
    "delayMinutes": 0,
    "delayCategory": "Early 0",
    "lastUpdated": "2025-10-25T11:14:23.000Z"
  },
  {
    "id": 25,
    "flightNumber": "102",
    "date": "2025-10-25",
    "from": "LIM-Jorge Chavez Airport",
    "to": "BOG-El Dorado Airport",
    "status": "Landed",
    "etd": "06:45",
    "atd": "06:40",
    "airline": "Avianca",
    "delayMinutes": -5,
    "delayCategory": "Early 5",
    "lastUpdated": "2025-10-25T11:14:23.000Z"
  },
  {
    "id": 26,
    "flightNumber": "110",
    "date": "2025-10-25",
    "from": "MVD-Carrasco Airport",
    "to": "BOG-El Dorado Airport",
    "status": "Departed",
    "etd": "06:55",
    "atd": "06:54",
    "airline": "Avianca",
    "delayMinutes": -1,
    "delayCategory": "Early 1",
    "lastUpdated": "2025-10-25T11:14:23.000Z"
  },
  {
    "id": 27,
    "flightNumber": "8545",
    "date": "2025-10-25",
    "from": "BAQ-Ernesto Cortissoz Airport",
    "to": "MDE-Jose Maria Cordova Airport",
    "status": "Landed",
    "etd": "06:56",
    "atd": "06:53",
    "airline": "Avianca",
    "delayMinutes": -3,
    "delayCategory": "Early 3",
    "lastUpdated": "2025-10-25T11:14:23.000Z"
  },
  {
    "id": 28,
    "flightNumber": "154",
    "date": "2025-10-25",
    "from": "AEP-Jorge Newbery Airfield",
    "to": "BOG-El Dorado Airport",
    "status": "Departed",
    "etd": "07:00",
    "atd": "08:26",
    "airline": "Avianca",
    "delayMinutes": 86,
    "delayCategory": "+ 86",
    "lastUpdated": "2025-10-25T11:14:23.000Z"
  },
  {
    "id": 29,
    "flightNumber": "262",
    "date": "2025-10-25",
    "from": "BOG-El Dorado Airport",
    "to": "ORD-O'Hare Airport",
    "status": "Departed",
    "etd": "07:00",
    "atd": "06:59",
    "airline": "Avianca",
    "delayMinutes": -1,
    "delayCategory": "Early 1",
    "lastUpdated": "2025-10-25T11:14:23.000Z"
  },
  {
    "id": 30,
    "flightNumber": "128",
    "date": "2025-10-25",
    "from": "BOG-El Dorado Airport",
    "to": "PUJ-Punta Cana Airport",
    "status": "Landed",
    "etd": "07:00",
    "atd": "07:07",
    "airline": "Avianca",
    "delayMinutes": 7,
    "delayCategory": "+ 7",
    "lastUpdated": "2025-10-25T11:14:23.000Z"
  },
  {
    "id": 31,
    "flightNumber": "210",
    "date": "2025-10-25",
    "from": "BOG-El Dorado Airport",
    "to": "JFK-John F Kennedy",
    "status": "Departed",
    "etd": "07:00",
    "atd": "07:19",
    "airline": "Avianca",
    "delayMinutes": 19,
    "delayCategory": "+ 19",
    "lastUpdated": "2025-10-25T11:14:23.000Z"
  },
  {
    "id": 32,
    "flightNumber": "98",
    "date": "2025-10-25",
    "from": "SCL-Arturo Merino Benítez Airport",
    "to": "BOG-El Dorado Airport",
    "status": "Departed",
    "etd": "07:10",
    "atd": "07:21",
    "airline": "Wamos",
    "delayMinutes": 11,
    "delayCategory": "+ 11",
    "lastUpdated": "2025-10-25T11:14:23.000Z"
  },
  {
    "id": 33,
    "flightNumber": "142",
    "date": "2025-10-25",
    "from": "BOG-El Dorado Airport",
    "to": "CCS-Maiquetía Simón Bolívar Airport",
    "status": "Landed",
    "etd": "07:10",
    "atd": "07:28",
    "airline": "Avianca",
    "delayMinutes": 18,
    "delayCategory": "+ 18",
    "lastUpdated": "2025-10-25T11:14:23.000Z"
  },
  {
    "id": 34,
    "flightNumber": "185",
    "date": "2025-10-25",
    "from": "BOG-El Dorado Airport",
    "to": "GRU-Sao Pablo- Guarulhos Airport",
    "status": "Departed",
    "etd": "07:15",
    "atd": "07:28",
    "airline": "Avianca",
    "delayMinutes": 13,
    "delayCategory": "+ 13",
    "lastUpdated": "2025-10-25T11:14:23.000Z"
  },
  {
    "id": 35,
    "flightNumber": "70",
    "date": "2025-10-25",
    "from": "BOG-El Dorado Airport",
    "to": "SAL-El Salvador Airport",
    "status": "Landed",
    "etd": "07:15",
    "atd": "07:14",
    "airline": "Avianca",
    "delayMinutes": -1,
    "delayCategory": "Early 1",
    "lastUpdated": "2025-10-25T11:14:23.000Z"
  },
  {
    "id": 36,
    "flightNumber": "260",
    "date": "2025-10-25",
    "from": "GIG-Galeao Airport",
    "to": "BOG-El Dorado Airport",
    "status": "Departed",
    "etd": "07:25",
    "atd": "07:22",
    "airline": "Avianca",
    "delayMinutes": -3,
    "delayCategory": "Early 3",
    "lastUpdated": "2025-10-25T11:14:23.000Z"
  },
  {
    "id": 37,
    "flightNumber": "246",
    "date": "2025-10-25",
    "from": "BOG-El Dorado Airport",
    "to": "IAD-Washington Dulles Airport",
    "status": "Departed",
    "etd": "07:30",
    "atd": "07:45",
    "airline": "Avianca",
    "delayMinutes": 15,
    "delayCategory": "+ 15",
    "lastUpdated": "2025-10-25T11:14:23.000Z"
  },
  {
    "id": 38,
    "flightNumber": "310",
    "date": "2025-10-25",
    "from": "SAL-El Salvador Airport",
    "to": "MIA-Miami Airport",
    "status": "Landed",
    "etd": "07:35",
    "atd": "07:40",
    "airline": "Taca",
    "delayMinutes": 5,
    "delayCategory": "+ 5",
    "lastUpdated": "2025-10-25T11:14:23.000Z"
  },
  {
    "id": 39,
    "flightNumber": "8342",
    "date": "2025-10-25",
    "from": "COR-Ingeniero Ambrosio Taravella Airport",
    "to": "BOG-El Dorado Airport",
    "status": "Departed",
    "etd": "07:35",
    "atd": "07:34",
    "airline": "Avianca Ecuador",
    "delayMinutes": -1,
    "delayCategory": "Early 1",
    "lastUpdated": "2025-10-25T11:14:23.000Z"
  },
  {
    "id": 40,
    "flightNumber": "8342",
    "date": "2025-10-25",
    "from": "BOG-El Dorado Airport",
    "to": "UIO-Mariscal Sucre Airport",
    "status": "Confirmed",
    "etd": "13:00",
    "atd": "13:00",
    "airline": "Avianca Ecuador",
    "delayMinutes": null,
    "delayCategory": null,
    "lastUpdated": "2025-10-25T11:14:23.000Z"
  },
  {
    "id": 41,
    "flightNumber": "105",
    "date": "2025-10-25",
    "from": "BOG-El Dorado Airport",
    "to": "CUZ-Alejandro Velasco Astete Airport",
    "status": "Landed",
    "etd": "07:40",
    "atd": "07:41",
    "airline": "Avianca",
    "delayMinutes": 1,
    "delayCategory": "+ 1",
    "lastUpdated": "2025-10-25T11:14:23.000Z"
  },
  {
    "id": 42,
    "flightNumber": "105",
    "date": "2025-10-25",
    "from": "CUZ-Alejandro Velasco Astete Airport",
    "to": "LPB-El Alto Airport",
    "status": "Confirmed",
    "etd": "12:05",
    "atd": "12:05",
    "airline": "Avianca",
    "delayMinutes": null,
    "delayCategory": null,
    "lastUpdated": "2025-10-25T11:14:23.000Z"
  },
  {
    "id": 43,
    "flightNumber": "1691",
    "date": "2025-10-25",
    "from": "MEC-Eloy Alfaro Airport",
    "to": "UIO-Mariscal Sucre Airport",
    "status": "Landed",
    "etd": "07:40",
    "atd": "07:25",
    "airline": "Avianca Ecuador",
    "delayMinutes": -15,
    "delayCategory": "Early 15",
    "lastUpdated": "2025-10-25T11:14:23.000Z"
  },
  {
    "id": 44,
    "flightNumber": "440",
    "date": "2025-10-25",
    "from": "SAL-El Salvador Airport",
    "to": "DFW-Dallas/Fort Worth Airport",
    "status": "Departed",
    "etd": "07:40",
    "atd": "07:40",
    "airline": "Taca",
    "delayMinutes": 0,
    "delayCategory": "Early 0",
    "lastUpdated": "2025-10-25T11:14:23.000Z"
  },
  {
    "id": 45,
    "flightNumber": "536",
    "date": "2025-10-25",
    "from": "SAL-El Salvador Airport",
    "to": "SAP-Ramon Villeda Morales Airport",
    "status": "Landed",
    "etd": "07:40",
    "atd": "07:42",
    "airline": "Taca",
    "delayMinutes": 2,
    "delayCategory": "+ 2",
    "lastUpdated": "2025-10-25T11:14:23.000Z"
  },
  {
    "id": 46,
    "flightNumber": "4883",
    "date": "2025-10-25",
    "from": "VVC-La Vanguardia Airport",
    "to": "BOG-El Dorado Airport",
    "status": "Landed",
    "etd": "07:45",
    "atd": "07:40",
    "airline": "Clic para avianca Express",
    "delayMinutes": -5,
    "delayCategory": "Early 5",
    "lastUpdated": "2025-10-25T11:14:23.000Z"
  },
  {
    "id": 47,
    "flightNumber": "5",
    "date": "2025-10-25",
    "from": "MIA-Miami Airport",
    "to": "BOG-El Dorado Airport",
    "status": "Departed",
    "etd": "07:55",
    "atd": "08:52",
    "airline": "Avianca",
    "delayMinutes": 57,
    "delayCategory": "+ 57",
    "lastUpdated": "2025-10-25T11:14:23.000Z"
  },
  {
    "id": 48,
    "flightNumber": "2",
    "date": "2025-10-25",
    "from": "BAQ-Ernesto Cortissoz Airport",
    "to": "MIA-Miami Airport",
    "status": "Landed",
    "etd": "08:00",
    "atd": "08:00",
    "airline": "Avianca",
    "delayMinutes": 0,
    "delayCategory": "Early 0",
    "lastUpdated": "2025-10-25T11:14:23.000Z"
  },
  {
    "id": 49,
    "flightNumber": "368",
    "date": "2025-10-25",
    "from": "SAL-El Salvador Airport",
    "to": "IAH-George Bush Intercontinental Airport",
    "status": "Departed",
    "etd": "08:00",
    "atd": "07:56",
    "airline": "Taca",
    "delayMinutes": -4,
    "delayCategory": "Early 4",
    "lastUpdated": "2025-10-25T11:14:23.000Z"
  },
  {
    "id": 50,
    "flightNumber": "522",
    "date": "2025-10-25",
    "from": "SAL-El Salvador Airport",
    "to": "LAX-Los Angeles Airport",
    "status": "Departed",
    "etd": "08:00",
    "atd": "08:00",
    "airline": "Taca",
    "delayMinutes": 0,
    "delayCategory": "Early 0",
    "lastUpdated": "2025-10-25T11:14:23.000Z"
  },
  {
    "id": 51,
    "flightNumber": "626",
    "date": "2025-10-25",
    "from": "SAL-El Salvador Airport",
    "to": "YYZ-Toronto Pearson Airport",
    "status": "Departed",
    "etd": "08:10",
    "atd": "08:02",
    "airline": "Avianca Costa Rica",
    "delayMinutes": -8,
    "delayCategory": "Early 8",
    "lastUpdated": "2025-10-25T11:14:23.000Z"
  },
  {
    "id": 52,
    "flightNumber": "8484",
    "date": "2025-10-25",
    "from": "BOG-El Dorado Airport",
    "to": "SMR-Simon Bolivar Airport",
    "status": "Landed",
    "etd": "08:14",
    "atd": "08:12",
    "airline": "Avianca",
    "delayMinutes": -2,
    "delayCategory": "Early 2",
    "lastUpdated": "2025-10-25T11:14:23.000Z"
  },
  {
    "id": 53,
    "flightNumber": "268",
    "date": "2025-10-25",
    "from": "MDE-Jose Maria Cordova Airport",
    "to": "CUN-Cancun Airport",
    "status": "Departed",
    "etd": "08:15",
    "atd": "09:00",
    "airline": "Avianca",
    "delayMinutes": 45,
    "delayCategory": "+ 45",
    "lastUpdated": "2025-10-25T11:14:23.000Z"
  },
  {
    "id": 54,
    "flightNumber": "8550",
    "date": "2025-10-25",
    "from": "BOG-El Dorado Airport",
    "to": "AUC-Santiago Pérez Airport",
    "status": "Landed",
    "etd": "08:25",
    "atd": "08:19",
    "airline": "Avianca",
    "delayMinutes": -6,
    "delayCategory": "Early 6",
    "lastUpdated": "2025-10-25T11:14:23.000Z"
  },
  {
    "id": 55,
    "flightNumber": "4812",
    "date": "2025-10-25",
    "from": "BOG-El Dorado Airport",
    "to": "IPI-San Luis Airport",
    "status": "Landed",
    "etd": "08:29",
    "atd": "08:35",
    "airline": "Avianca",
    "delayMinutes": 6,
    "delayCategory": "+ 6",
    "lastUpdated": "2025-10-25T11:14:23.000Z"
  },
  {
    "id": 56,
    "flightNumber": "229",
    "date": "2025-10-25",
    "from": "CDG-Paris Charles de Gaulle Airport",
    "to": "BOG-El Dorado Airport",
    "status": "Departed",
    "etd": "08:45",
    "atd": "08:40",
    "airline": "Avianca",
    "delayMinutes": -5,
    "delayCategory": "Early 5",
    "lastUpdated": "2025-10-25T11:14:23.000Z"
  },
  {
    "id": 57,
    "flightNumber": "9492",
    "date": "2025-10-25",
    "from": "LET-Alfredo Vasquez Cobo Airport",
    "to": "BOG-El Dorado Airport",
    "status": "Landed",
    "etd": "08:58",
    "atd": "08:59",
    "airline": "Avianca",
    "delayMinutes": 1,
    "delayCategory": "+ 1",
    "lastUpdated": "2025-10-25T11:14:23.000Z"
  },
  {
    "id": 58,
    "flightNumber": "36",
    "date": "2025-10-25",
    "from": "BOG-El Dorado Airport",
    "to": "FLL-Fort Lauderdale/Hollywood Airport",
    "status": "Departed",
    "etd": "09:00",
    "atd": "09:03",
    "airline": "Avianca",
    "delayMinutes": 3,
    "delayCategory": "+ 3",
    "lastUpdated": "2025-10-25T11:14:23.000Z"
  },
  {
    "id": 59,
    "flightNumber": "227",
    "date": "2025-10-25",
    "from": "BOS-Logan Airport",
    "to": "BOG-El Dorado Airport",
    "status": "Departed",
    "etd": "09:00",
    "atd": "08:51",
    "airline": "Avianca",
    "delayMinutes": -9,
    "delayCategory": "Early 9",
    "lastUpdated": "2025-10-25T11:14:23.000Z"
  },
  {
    "id": 60,
    "flightNumber": "24",
    "date": "2025-10-25",
    "from": "MDE-Jose Maria Cordova Airport",
    "to": "SJO-Juan Santamaria Airport",
    "status": "Landed",
    "etd": "09:05",
    "atd": "09:05",
    "airline": "Avianca",
    "delayMinutes": 0,
    "delayCategory": "Early 0",
    "lastUpdated": "2025-10-25T11:14:23.000Z"
  },
  {
    "id": 61,
    "flightNumber": "4880",
    "date": "2025-10-25",
    "from": "BOG-El Dorado Airport",
    "to": "VVC-La Vanguardia Airport",
    "status": "Landed",
    "etd": "09:10",
    "atd": "09:15",
    "airline": "Clic para avianca Express",
    "delayMinutes": 5,
    "delayCategory": "+ 5",
    "lastUpdated": "2025-10-25T11:14:23.000Z"
  }
]